logaut/__init__.py
logaut/_registry.py
logaut/backends/__init__.py
logaut/backends/base.py
logaut/backends/common/__init__.py
logaut/backends/common/find_atoms/__init__.py
logaut/backends/common/find_atoms/base.py
logaut/backends/common/find_atoms/ldl.py
logaut/backends/common/find_atoms/ltl.py
logaut/backends/common/process_mona_output.py
logaut/backends/common/utils.py
logaut/backends/ltlf2dfa/__init__.py
logaut/backends/ltlf2dfa/core.py
logaut/backends/ltlf2dfa/to_ltlf2dfa_formula.py
logaut/backends/lydia/__init__.py
logaut/backends/lydia/_lydia_utils.py
logaut/backends/lydia/core.py
logaut/backends/lydia/to_lydia_grammar.py
logaut/core.py
logaut/exceptions.py
logaut/helpers.py
logaut-0.2.0.dist-info/LICENSE
logaut-0.2.0.dist-info/METADATA
logaut-0.2.0.dist-info/WHEEL
logaut-0.2.0.dist-info/RECORD
