Metadata-Version: 2.1
Name: logaut
Version: 0.2.0
Summary: From logic to automata.
Home-page: https://marcofavorito.me/logaut
License: GPL-3.0-or-later
Author: Marco Favorito
Author-email: marco.favorito@gmail.com
Requires-Python: >=3.8,<4.0
Classifier: Development Status :: 2 - Pre-Alpha
Classifier: Intended Audience :: Developers
Classifier: License :: OSI Approved :: GNU General Public License v3 or later (GPLv3+)
Classifier: License :: OSI Approved :: GNU Lesser General Public License v3 or later (LGPLv3+)
Classifier: Natural Language :: English
Classifier: Programming Language :: Python :: 3
Classifier: Programming Language :: Python :: 3.8
Classifier: Programming Language :: Python :: 3.9
Classifier: Programming Language :: Python :: 3.10
Classifier: Programming Language :: Python :: 3.11
Classifier: Programming Language :: Python :: 3.7
Requires-Dist: pylogics (>=0.2.1,<0.3.0)
Requires-Dist: pythomata (>=0.3.2,<0.4.0)
Project-URL: Bug Tracker, https://github.com/whitemech/logaut/issues
Project-URL: Documentation, https://marcofavorito.me/logaut
Project-URL: Pull Requests, https://github.com/whitemech/logaut/pulls
Project-URL: Repository, https://github.com/whitemech/logaut.git
